pymusician/__init__.py
pymusician/_pymusician.py
pymusician/constants.py
pymusician/utils.py
pymusician/data/modes.json
pymusician-1.0.1.dist-info/LICENSE
pymusician-1.0.1.dist-info/METADATA
pymusician-1.0.1.dist-info/WHEEL
pymusician-1.0.1.dist-info/top_level.txt
pymusician-1.0.1.dist-info/RECORD
