Metadata-Version: 2.1
Name: pymusician
Version: 1.0.1
Summary: A python package for music composition and analysis.
Home-page: https://github.com/ScottMorse/PyMusician
Author: Scott Morse
Author-email: scottmorsedev@gmail.com
License: Apache
Platform: UNKNOWN
Requires-Python: >3.6
Requires-Dist: numpy
